{
    "pageNumber": 37,
    "data": [
        {
            "id": "82818641",
            "title": "Junaid Jamshed Last Bayan at Rehankot",
            "date_created": "1481141166",
            "loginId": "1758823",
            "tags": "",
            "description": "Junaid Jamshed Last Bayan at Rehankot junaid jamshed naat, junaid jamshed passed away, junaid jamshed naat 2016, junaid jamshed bayan, junaid jamshed ...",
            "asset": {
                "type": "youtube",
                "thumbnailUrl": "https:\/\/i.ytimg.com\/vi\/Zb79jR-tifg\/hqdefault.jpg",
                "uploadDate": 1481141166,
                "videoId": "Zb79jR-tifg",
                "title": "Junaid Jamshed Last Bayan at Rehankot",
                "description": "Junaid Jamshed Last Bayan at Rehankot junaid jamshed naat, junaid jamshed passed away, junaid jamshed naat 2016, junaid jamshed bayan, junaid jamshed ...",
                "author": "On demand",
                "mediaDuration": 1069,
                "prettyDuration": "00:17:49",
                "views": "53327"
            },
            "parentId": "85595609",
            "url": "\/qweqwewqeasds\/junaid-jamshed-last-bayan-at-rehankot\/85595609-82818641"
        },
        {
            "id": "82818640",
            "title": "THE LAST GUARDIAN #8 - Ajudando Trico! (PS4 Pro Gameplay Portugu\u00eas)",
            "date_created": "1481142079",
            "loginId": "1758823",
            "tags": "",
            "description": "V\u00eddeo gameplay do jogo The Last Guardian, game exclusivo de PlayStation 4 dispon\u00edvel com legendas em Portugu\u00eas PT-BR. Assista tamb\u00e9m a minha s\u00e9rie de ...",
            "asset": {
                "type": "youtube",
                "thumbnailUrl": "https:\/\/i.ytimg.com\/vi\/Md_9Uc2m8gE\/hqdefault.jpg",
                "uploadDate": 1481142079,
                "videoId": "Md_9Uc2m8gE",
                "title": "THE LAST GUARDIAN #8 - Ajudando Trico! (PS4 Pro Gameplay Portugu\u00eas)",
                "description": "V\u00eddeo gameplay do jogo The Last Guardian, game exclusivo de PlayStation 4 dispon\u00edvel com legendas em Portugu\u00eas PT-BR. Assista tamb\u00e9m a minha s\u00e9rie de ...",
                "author": "BRKsEDU",
                "mediaDuration": 1636,
                "prettyDuration": "00:27:16",
                "views": "133531"
            },
            "parentId": "85595609",
            "url": "\/qweqwewqeasds\/the-last-guardian-8-ajudando-trico-ps4-pro-gameplay-portugu\u00eas\/85595609-82818640"
        },
        {
            "id": "82818639",
            "title": "THE LAST GUARDIAN Part 1: Unser fabelhafter Freund Trico",
            "date_created": "1481142600",
            "loginId": "1758823",
            "tags": "",
            "description": "Let's Play THE LAST GUARDIAN [Deutsch \u2662 Blind \u2662 1440p@60 FPS] Part 1: Unser fabelhafter Freund Trico \u25bb Meinen Kanal abonnieren: http:\/\/goo.gl\/440Rdg ...",
            "asset": {
                "type": "youtube",
                "thumbnailUrl": "https:\/\/i.ytimg.com\/vi\/6rwBwqpA5aU\/hqdefault.jpg",
                "uploadDate": 1481142600,
                "videoId": "6rwBwqpA5aU",
                "title": "THE LAST GUARDIAN Part 1: Unser fabelhafter Freund Trico",
                "description": "Let's Play THE LAST GUARDIAN [Deutsch \u2662 Blind \u2662 1440p@60 FPS] Part 1: Unser fabelhafter Freund Trico \u25bb Meinen Kanal abonnieren: http:\/\/goo.gl\/440Rdg ...",
                "author": "Domtendo",
                "mediaDuration": 1678,
                "prettyDuration": "00:27:58",
                "views": "68190"
            },
            "parentId": "85595609",
            "url": "\/qweqwewqeasds\/the-last-guardian-part-1-unser-fabelhafter-freund-trico\/85595609-82818639"
        },
        {
            "id": "82818638",
            "title": "THE LAST GUARDIAN con mi Sra Madre",
            "date_created": "1481146509",
            "loginId": "1758823",
            "tags": "",
            "description": "Aqu\u00ed un video de The Last Guardian, traere otro video por lo menos en el que explicar\u00e9 mi opini\u00f3n cuando me lo pase, creo que este juego se merece una ...",
            "asset": {
                "type": "youtube",
                "thumbnailUrl": "https:\/\/i.ytimg.com\/vi\/sW7MTzdODcQ\/hqdefault.jpg",
                "uploadDate": 1481146509,
                "videoId": "sW7MTzdODcQ",
                "title": "THE LAST GUARDIAN con mi Sra Madre",
                "description": "Aqu\u00ed un video de The Last Guardian, traere otro video por lo menos en el que explicar\u00e9 mi opini\u00f3n cuando me lo pase, creo que este juego se merece una ...",
                "author": "aLexBY11",
                "mediaDuration": 931,
                "prettyDuration": "00:15:31",
                "views": "263605"
            },
            "parentId": "85595609",
            "url": "\/qweqwewqeasds\/the-last-guardian-con-mi-sra-madre\/85595609-82818638"
        },
        {
            "id": "82818652",
            "title": "HOW LONG WILL MOURINHO LAST? MAN UTD NEWS",
            "date_created": "1481147987",
            "loginId": "1758823",
            "tags": "",
            "description": "How long will Jose Mourinho last as Manchester United manager? Have YOUR say Man United fans on all the latest Man Utd news on The United Stand fan call ...",
            "asset": {
                "type": "youtube",
                "thumbnailUrl": "https:\/\/i.ytimg.com\/vi\/CudVsqrm7VA\/hqdefault.jpg",
                "uploadDate": 1481147987,
                "videoId": "CudVsqrm7VA",
                "title": "HOW LONG WILL MOURINHO LAST? MAN UTD NEWS",
                "description": "How long will Jose Mourinho last as Manchester United manager? Have YOUR say Man United fans on all the latest Man Utd news on The United Stand fan call ...",
                "author": "The United Stand",
                "mediaDuration": 3141,
                "prettyDuration": "00:52:21",
                "views": "10182"
            },
            "parentId": "85595609",
            "url": "\/qweqwewqeasds\/how-long-will-mourinho-last-man-utd-news\/85595609-82818652"
        },
        {
            "id": "82818651",
            "title": "MY DOG IS IN THIS GAME?! - The Last Guardian - Part 3",
            "date_created": "1481148212",
            "loginId": "1758823",
            "tags": "",
            "description": "WE ARE BACK WITH MORE LAST GUARDIAN GAMEPLAY PART 3 [Ad:] Check out my current Giveaway w\/ G2A: ...",
            "asset": {
                "type": "youtube",
                "thumbnailUrl": "https:\/\/i.ytimg.com\/vi\/rZjtMV83KVM\/hqdefault.jpg",
                "uploadDate": 1481148212,
                "videoId": "rZjtMV83KVM",
                "title": "MY DOG IS IN THIS GAME?! - The Last Guardian - Part 3",
                "description": "WE ARE BACK WITH MORE LAST GUARDIAN GAMEPLAY PART 3 [Ad:] Check out my current Giveaway w\/ G2A: ...",
                "author": "PewDiePie",
                "mediaDuration": 1839,
                "prettyDuration": "00:30:39",
                "views": "2060734"
            },
            "parentId": "85595609",
            "url": "\/qweqwewqeasds\/my-dog-is-in-this-game-the-last-guardian-part-3\/85595609-82818651"
        },
        {
            "id": "82818650",
            "title": "UFC 206: Matt Brown Talks About Going to Jail His Last Time in Canada",
            "date_created": "1481153852",
            "loginId": "1758823",
            "tags": "",
            "description": "http:\/\/fightnetwork.com\/ - Matt Brown speaks with the media ahead of his UFC 206 match-up against Donald Cerrone about working with Duane Ludwig, ...",
            "asset": {
                "type": "youtube",
                "thumbnailUrl": "https:\/\/i.ytimg.com\/vi\/I-9emdmH0vg\/hqdefault.jpg",
                "uploadDate": 1481153852,
                "videoId": "I-9emdmH0vg",
                "title": "UFC 206: Matt Brown Talks About Going to Jail His Last Time in Canada",
                "description": "http:\/\/fightnetwork.com\/ - Matt Brown speaks with the media ahead of his UFC 206 match-up against Donald Cerrone about working with Duane Ludwig, ...",
                "author": "Fight Network",
                "mediaDuration": 548,
                "prettyDuration": "00:09:08",
                "views": "10660"
            },
            "parentId": "85595609",
            "url": "\/qweqwewqeasds\/ufc-206-matt-brown-talks-about-going-to-jail-his-last-time-in-canada\/85595609-82818650"
        },
        {
            "id": "82818637",
            "title": "The Last Guardian",
            "date_created": "1481155021",
            "loginId": "1758823",
            "tags": "",
            "description": "This is the greatest marching of All Time.",
            "asset": {
                "type": "youtube",
                "thumbnailUrl": "https:\/\/i.ytimg.com\/vi\/mRm8q9pONOw\/hqdefault.jpg",
                "uploadDate": 1481155021,
                "videoId": "mRm8q9pONOw",
                "title": "The Last Guardian",
                "description": "This is the greatest marching of All Time.",
                "author": "penguinz0",
                "mediaDuration": 252,
                "prettyDuration": "00:04:12",
                "views": "180371"
            },
            "parentId": "85595609",
            "url": "\/qweqwewqeasds\/the-last-guardian\/85595609-82818637"
        },
        {
            "id": "82818636",
            "title": "The Last of Us 2 , Transformers 5 e Natal",
            "date_created": "1481155201",
            "loginId": "1758823",
            "tags": "",
            "description": "MEU NOVO CANAL - https:\/\/www.youtube.com\/watch?v=5uwoycAT7uk.",
            "asset": {
                "type": "youtube",
                "thumbnailUrl": "https:\/\/i.ytimg.com\/vi\/Z64J4jfV2-Q\/hqdefault.jpg",
                "uploadDate": 1481155201,
                "videoId": "Z64J4jfV2-Q",
                "title": "The Last of Us 2 , Transformers 5 e Natal",
                "description": "MEU NOVO CANAL - https:\/\/www.youtube.com\/watch?v=5uwoycAT7uk.",
                "author": "Gameplayrj",
                "mediaDuration": 308,
                "prettyDuration": "00:05:08",
                "views": "172548"
            },
            "parentId": "85595609",
            "url": "\/qweqwewqeasds\/the-last-of-us-2-transformers-5-e-natal\/85595609-82818636"
        },
        {
            "id": "82818635",
            "title": "LMAO! | Avatar The Last Hoodbender | Reaction",
            "date_created": "1481159393",
            "loginId": "1758823",
            "tags": "",
            "description": "Original Video https:\/\/www.youtube.com\/watch?v=NOEy_9DgLvU TWITCH https:\/\/www.twitch.tv\/im_dontai YouNow https:\/\/www.younow.com\/ImDontai ...",
            "asset": {
                "type": "youtube",
                "thumbnailUrl": "https:\/\/i.ytimg.com\/vi\/v-3d94iauWA\/hqdefault.jpg",
                "uploadDate": 1481159393,
                "videoId": "v-3d94iauWA",
                "title": "LMAO! | Avatar The Last Hoodbender | Reaction",
                "description": "Original Video https:\/\/www.youtube.com\/watch?v=NOEy_9DgLvU TWITCH https:\/\/www.twitch.tv\/im_dontai YouNow https:\/\/www.younow.com\/ImDontai ...",
                "author": "ImDontai",
                "mediaDuration": 763,
                "prettyDuration": "00:12:43",
                "views": "22674"
            },
            "parentId": "85595609",
            "url": "\/qweqwewqeasds\/lmao-avatar-the-last-hoodbender-reaction\/85595609-82818635"
        },
        {
            "id": "82818634",
            "title": "RDCworld1 \"AVATAR THE LAST HOODBENDER\" Reaction!!!",
            "date_created": "1481160694",
            "loginId": "1758823",
            "tags": "",
            "description": "GET YOUR LIMITED EDITION \"Knight White\" LOYALIST HOODIE NOW!!! ONLY 100 AVAILABLE!!! : https:\/\/creatorslabel.com\/collections\/couplesreact In today's ...",
            "asset": {
                "type": "youtube",
                "thumbnailUrl": "https:\/\/i.ytimg.com\/vi\/yabvoPTcO-o\/hqdefault.jpg",
                "uploadDate": 1481160694,
                "videoId": "yabvoPTcO-o",
                "title": "RDCworld1 \"AVATAR THE LAST HOODBENDER\" Reaction!!!",
                "description": "GET YOUR LIMITED EDITION \"Knight White\" LOYALIST HOODIE NOW!!! ONLY 100 AVAILABLE!!! : https:\/\/creatorslabel.com\/collections\/couplesreact In today's ...",
                "author": "Dwayne N Jazz",
                "mediaDuration": 614,
                "prettyDuration": "00:10:14",
                "views": "99799"
            },
            "parentId": "85595609",
            "url": "\/qweqwewqeasds\/rdcworld1-avatar-the-last-hoodbender-reaction\/85595609-82818634"
        },
        {
            "id": "82818633",
            "title": "The Last of Us Part 2: Theory, Analysis, and Details You Might Have Missed",
            "date_created": "1481162400",
            "loginId": "1758823",
            "tags": "",
            "description": "There's a popular fan theory about Joel and Ellie, but we have a different one. Watch The Last of Us Part 2 Official Trailer here!",
            "asset": {
                "type": "youtube",
                "thumbnailUrl": "https:\/\/i.ytimg.com\/vi\/4GC4x0I0g4I\/hqdefault.jpg",
                "uploadDate": 1481162400,
                "videoId": "4GC4x0I0g4I",
                "title": "The Last of Us Part 2: Theory, Analysis, and Details You Might Have Missed",
                "description": "There's a popular fan theory about Joel and Ellie, but we have a different one. Watch The Last of Us Part 2 Official Trailer here!",
                "author": "IGN",
                "mediaDuration": 426,
                "prettyDuration": "00:07:06",
                "views": "371469"
            },
            "parentId": "85595609",
            "url": "\/qweqwewqeasds\/the-last-of-us-part-2-theory-analysis-and-details-you-might-have-missed\/85595609-82818633"
        },
        {
            "id": "82818632",
            "title": "NUEVOS PELIGROS NOS ACECHAN!! THE LAST GUARDIAN #2",
            "date_created": "1481162829",
            "loginId": "1758823",
            "tags": "",
            "description": "CAMISETAS OFICIALES: http:\/\/mundotubers.com\/31-fargan Te gusta? Click Aqui (Suscr\u00edbete): http:\/\/goo.gl\/HIujg0 \u25bd\u25bd\u25bd\u25bd\u25bd\u25bd REDES SOCIALES ...",
            "asset": {
                "type": "youtube",
                "thumbnailUrl": "https:\/\/i.ytimg.com\/vi\/kvlL406QvFY\/hqdefault.jpg",
                "uploadDate": 1481162829,
                "videoId": "kvlL406QvFY",
                "title": "NUEVOS PELIGROS NOS ACECHAN!! THE LAST GUARDIAN #2",
                "description": "CAMISETAS OFICIALES: http:\/\/mundotubers.com\/31-fargan Te gusta? Click Aqui (Suscr\u00edbete): http:\/\/goo.gl\/HIujg0 \u25bd\u25bd\u25bd\u25bd\u25bd\u25bd REDES SOCIALES ...",
                "author": "xFaRgAnx YT",
                "mediaDuration": 7550,
                "prettyDuration": "02:05:50",
                "views": "59925"
            },
            "parentId": "85595609",
            "url": "\/qweqwewqeasds\/nuevos-peligros-nos-acechan-the-last-guardian-2\/85595609-82818632"
        },
        {
            "id": "82818631",
            "title": "Junaid Jamshed's Last Naat Sharif Before His Death [Emotional]",
            "date_created": "1481171036",
            "loginId": "1758823",
            "tags": "",
            "description": "Junaid Jamshed's Last Naat Sharif Before His Death [Emotional]",
            "asset": {
                "type": "youtube",
                "thumbnailUrl": "https:\/\/i.ytimg.com\/vi\/7ptGDiEM27g\/hqdefault.jpg",
                "uploadDate": 1481171036,
                "videoId": "7ptGDiEM27g",
                "title": "Junaid Jamshed's Last Naat Sharif Before His Death [Emotional]",
                "description": "Junaid Jamshed's Last Naat Sharif Before His Death [Emotional]",
                "author": "BestOfYT",
                "mediaDuration": 222,
                "prettyDuration": "00:03:42",
                "views": "65153"
            },
            "parentId": "85595609",
            "url": "\/qweqwewqeasds\/junaid-jamshed-s-last-naat-sharif-before-his-death-emotional\/85595609-82818631"
        },
        {
            "id": "82818630",
            "title": "AVATAR THE LAST HOODBENDER UNLEASHED!! Live REACTION AnimeAnalyst!",
            "date_created": "1481171606",
            "loginId": "1758823",
            "tags": "",
            "description": "Avatar the Last Hoodbender Live Reaction RDCworld 1 https:\/\/youtu.be\/NOEy_9DgLvU Boxing, Sneaking, Weaving and Shooting nation are in chaos. Only the ...",
            "asset": {
                "type": "youtube",
                "thumbnailUrl": "https:\/\/i.ytimg.com\/vi\/OGG3aqR6Dv0\/hqdefault.jpg",
                "uploadDate": 1481171606,
                "videoId": "OGG3aqR6Dv0",
                "title": "AVATAR THE LAST HOODBENDER UNLEASHED!! Live REACTION AnimeAnalyst!",
                "description": "Avatar the Last Hoodbender Live Reaction RDCworld 1 https:\/\/youtu.be\/NOEy_9DgLvU Boxing, Sneaking, Weaving and Shooting nation are in chaos. Only the ...",
                "author": "AnimeAnalyst",
                "mediaDuration": 627,
                "prettyDuration": "00:10:27",
                "views": "5722"
            },
            "parentId": "85595609",
            "url": "\/qweqwewqeasds\/avatar-the-last-hoodbender-unleashed-live-reaction-animeanalyst\/85595609-82818630"
        },
        {
            "id": "82818629",
            "title": "JUNAID JAMSHED LAST BAYAN 2016 before Death junaid bhai last moments junaid jamshed latest video",
            "date_created": "1481177629",
            "loginId": "1758823",
            "tags": "",
            "description": "JUNAID JAMSHED LAST BAYAN 2016 before Death junaid bhai last moments junaid jamshed latest viral video junaid jamshed last bayan before death junaid ...",
            "asset": {
                "type": "youtube",
                "thumbnailUrl": "https:\/\/i.ytimg.com\/vi\/CI0yKw-TkHc\/hqdefault.jpg",
                "uploadDate": 1481177629,
                "videoId": "CI0yKw-TkHc",
                "title": "JUNAID JAMSHED LAST BAYAN 2016 before Death junaid bhai last moments junaid jamshed latest video",
                "description": "JUNAID JAMSHED LAST BAYAN 2016 before Death junaid bhai last moments junaid jamshed latest viral video junaid jamshed last bayan before death junaid ...",
                "author": "Al Noor",
                "mediaDuration": 2465,
                "prettyDuration": "00:41:05",
                "views": "388676"
            },
            "parentId": "85595609",
            "url": "\/qweqwewqeasds\/junaid-jamshed-last-bayan-2016-before-death-junaid-bhai-last-moments-junaid-jamshed-latest-video\/85595609-82818629"
        },
        {
            "id": "82818628",
            "title": "Sasikala didn't Fulfill Jayalalithas Last Wish ! \u00a6 Tamil Cinema Seithigal",
            "date_created": "1481183448",
            "loginId": "1758823",
            "tags": "",
            "description": "Subscribe us http:\/\/goo.gl\/0Dympr google + http:\/\/goo.gl\/a9uzhe Twitter https:\/\/goo.gl\/XFRKrs Facebook https:\/\/goo.gl\/tGJi1u Website ...",
            "asset": {
                "type": "youtube",
                "thumbnailUrl": "https:\/\/i.ytimg.com\/vi\/SCGjCN8FYis\/hqdefault.jpg",
                "uploadDate": 1481183448,
                "videoId": "SCGjCN8FYis",
                "title": "Sasikala didn't Fulfill Jayalalithas Last Wish ! \u00a6 Tamil Cinema Seithigal",
                "description": "Subscribe us http:\/\/goo.gl\/0Dympr google + http:\/\/goo.gl\/a9uzhe Twitter https:\/\/goo.gl\/XFRKrs Facebook https:\/\/goo.gl\/tGJi1u Website ...",
                "author": "G Creation",
                "mediaDuration": 126,
                "prettyDuration": "00:02:06",
                "views": "22726"
            },
            "parentId": "85595609",
            "url": "\/qweqwewqeasds\/sasikala-didn-t-fulfill-jayalalithas-last-wish-tamil-cinema-seithigal\/85595609-82818628"
        },
        {
            "id": "82818627",
            "title": "Junaid Jamshed Last Full Speech(Bayan) In Chitral",
            "date_created": "1481186171",
            "loginId": "1758823",
            "tags": "",
            "description": "Junaid Jamshed Last Full Bayan In Chitral Junaid Jamshed (Urdu: \u062c\u0646\u06cc\u062f \u062c\u0645\u0634\u06cc\u062f  ; September 3, 1964 \u2013 December 7, 2016) was a Pakistani recording artist, ...",
            "asset": {
                "type": "youtube",
                "thumbnailUrl": "https:\/\/i.ytimg.com\/vi\/b87PABwLy-I\/hqdefault.jpg",
                "uploadDate": 1481186171,
                "videoId": "b87PABwLy-I",
                "title": "Junaid Jamshed Last Full Speech(Bayan) In Chitral",
                "description": "Junaid Jamshed Last Full Bayan In Chitral Junaid Jamshed (Urdu: \u062c\u0646\u06cc\u062f \u062c\u0645\u0634\u06cc\u062f  ; September 3, 1964 \u2013 December 7, 2016) was a Pakistani recording artist, ...",
                "author": "Al Mahira Production",
                "mediaDuration": 673,
                "prettyDuration": "00:11:13",
                "views": "4042"
            },
            "parentId": "85595609",
            "url": "\/qweqwewqeasds\/junaid-jamshed-last-full-speech-bayan-in-chitral\/85595609-82818627"
        },
        {
            "id": "82818626",
            "title": "\u041f\u0420\u041e\u0425\u041e\u0416\u0414\u0415\u041d\u0418\u0415 The Last Guardian #7 \u2014 \u0417\u041b\u041e\u0419 \u0422\u0420\u0418\u041a\u0423",
            "date_created": "1481207785",
            "loginId": "1758823",
            "tags": "",
            "description": "\u041f\u0420\u041e\u0425\u041e\u0416\u0414\u0415\u041d\u0418\u0415 The Last Guardian - https:\/\/goo.gl\/dTtl5s \u272a \u041b\u0423\u0427\u0428\u0418\u0419 \u041c\u0410\u0413\u0410\u0417\u0418\u041d \u0418\u0413\u0420 - https:\/\/www.g2a.com\/r\/g2apzr \u25bd !!! \u0420\u0410\u0417\u0412\u0415\u0420\u041d\u0418 !!! \u25bd \u041c\u0435\u043d\u044f \u043c\u043e\u0436\u043d\u043e...",
            "asset": {
                "type": "youtube",
                "thumbnailUrl": "https:\/\/i.ytimg.com\/vi\/bHXsd-UFGgc\/hqdefault.jpg",
                "uploadDate": 1481207785,
                "videoId": "bHXsd-UFGgc",
                "title": "\u041f\u0420\u041e\u0425\u041e\u0416\u0414\u0415\u041d\u0418\u0415 The Last Guardian #7 \u2014 \u0417\u041b\u041e\u0419 \u0422\u0420\u0418\u041a\u0423",
                "description": "\u041f\u0420\u041e\u0425\u041e\u0416\u0414\u0415\u041d\u0418\u0415 The Last Guardian - https:\/\/goo.gl\/dTtl5s \u272a \u041b\u0423\u0427\u0428\u0418\u0419 \u041c\u0410\u0413\u0410\u0417\u0418\u041d \u0418\u0413\u0420 - https:\/\/www.g2a.com\/r\/g2apzr \u25bd !!! \u0420\u0410\u0417\u0412\u0415\u0420\u041d\u0418 !!! \u25bd \u041c\u0435\u043d\u044f \u043c\u043e\u0436\u043d\u043e...",
                "author": "PomodorkaZR",
                "mediaDuration": 1964,
                "prettyDuration": "00:32:44",
                "views": "11606"
            },
            "parentId": "85595609",
            "url": "\/qweqwewqeasds\/\u041f\u0420\u041e\u0425\u041e\u0416\u0414\u0415\u041d\u0418\u0415-the-last-guardian-7-\u0417\u041b\u041e\u0419-\u0422\u0420\u0418\u041a\u0423\/85595609-82818626"
        },
        {
            "id": "82818625",
            "title": "THE LAST GUARDIAN : Un lien si particulier | LET'S PLAY FR #3",
            "date_created": "1481212802",
            "loginId": "1758823",
            "tags": "",
            "description": "The Last Guardian est enfin disponible, on continue de le d\u00e9couvrir ensemble avec une phase de jeu qui ne manque pas de charme ! \u25bb S'abonner \u00e0 la cha\u00eene ...",
            "asset": {
                "type": "youtube",
                "thumbnailUrl": "https:\/\/i.ytimg.com\/vi\/PePE2635xIg\/hqdefault.jpg",
                "uploadDate": 1481212802,
                "videoId": "PePE2635xIg",
                "title": "THE LAST GUARDIAN : Un lien si particulier | LET'S PLAY FR #3",
                "description": "The Last Guardian est enfin disponible, on continue de le d\u00e9couvrir ensemble avec une phase de jeu qui ne manque pas de charme ! \u25bb S'abonner \u00e0 la cha\u00eene ...",
                "author": "At0mium",
                "mediaDuration": 2599,
                "prettyDuration": "00:43:19",
                "views": "14276"
            },
            "parentId": "85595609",
            "url": "\/qweqwewqeasds\/the-last-guardian-un-lien-si-particulier-let-s-play-fr-3\/85595609-82818625"
        }
    ]
}