{
    "title": "Donny Deutsch: Fear Of The Status Quo Won Last Night | Morning Joe | MSNBC",
    "description": "Ben Ginsberg and Donny Deutsch discuss Donald Trump's unlikely rise to the White House. \u00bb Subscribe to MSNBC: http:\/\/on.msnbc.com\/SubscribeTomsnbc ...",
    "referenceId": "oRpp67HrwxQ",
    "date_created": "1478701690",
    "date_modified": "1478829832",
    "tags": "",
    "sourceId": "4",
    "VIDEO_LENGTH": "LONG",
    "status": "pending",
    "visibility": "1",
    "test_code6": null,
    "total_views": null,
    "id": "80152818",
    "loginId": "1758823",
    "entityType": "1",
    "sortOrder": "84",
    "entityIdParent": "85595609",
    "titleTextEncoded": "Donny-Deutsch-Fear-Of-The-Status-Quo-Won-Last-Night-Morning-Joe-MSNBC",
    "category": "",
    "duration": 344,
    "settings": "",
    "asset": {
        "type": "youtube",
        "thumbnailUrl": "https:\/\/i.ytimg.com\/vi\/oRpp67HrwxQ\/hqdefault.jpg",
        "uploadDate": 1478701690,
        "videoId": "oRpp67HrwxQ",
        "title": "Donny Deutsch: Fear Of The Status Quo Won Last Night | Morning Joe | MSNBC",
        "description": "Ben Ginsberg and Donny Deutsch discuss Donald Trump's unlikely rise to the White House. \u00bb Subscribe to MSNBC: http:\/\/on.msnbc.com\/SubscribeTomsnbc ...",
        "author": "MSNBC",
        "mediaDuration": 344,
        "prettyDuration": "00:05:44",
        "views": "30023"
    },
    "transcripts": "",
    "test_code": null,
    "test_code2": null,
    "test_code3": null,
    "test_code4": null,
    "test_code5": null
}