{
    "title": "The Last of Us 2 , Transformers 5 e Natal",
    "description": "MEU NOVO CANAL - https:\/\/www.youtube.com\/watch?v=5uwoycAT7uk.",
    "referenceId": "Z64J4jfV2-Q",
    "date_created": "1481155201",
    "date_modified": "1481573238",
    "tags": "",
    "sourceId": "4",
    "VIDEO_LENGTH": "LONG",
    "status": "pending",
    "visibility": "1",
    "test_code6": null,
    "total_views": null,
    "id": "82818636",
    "loginId": "1758823",
    "entityType": "1",
    "sortOrder": "748",
    "entityIdParent": "85595609",
    "titleTextEncoded": "The-Last-of-Us-2-Transformers-5-e-Natal",
    "category": "",
    "duration": 308,
    "settings": "",
    "asset": {
        "type": "youtube",
        "thumbnailUrl": "https:\/\/i.ytimg.com\/vi\/Z64J4jfV2-Q\/hqdefault.jpg",
        "uploadDate": 1481155201,
        "videoId": "Z64J4jfV2-Q",
        "title": "The Last of Us 2 , Transformers 5 e Natal",
        "description": "MEU NOVO CANAL - https:\/\/www.youtube.com\/watch?v=5uwoycAT7uk.",
        "author": "Gameplayrj",
        "mediaDuration": 308,
        "prettyDuration": "00:05:08",
        "views": "172548"
    },
    "transcripts": "",
    "test_code": null,
    "test_code2": null,
    "test_code3": null,
    "test_code4": null,
    "test_code5": null
}