{
    "title": "Last man on the moon Gene Cernan dies at 82",
    "description": "\"Eugene Cernan\":https:\/\/en.wikipedia.org\/wiki\/Eugene_Cernan the last man to walk on the moon as skipper of Apollo 17 in December 1972, has died at the age ...",
    "referenceId": "9Of8eqpZY8k",
    "date_created": "1484607970",
    "date_modified": "1484705016",
    "tags": "",
    "sourceId": "4",
    "VIDEO_LENGTH": "SHORT",
    "status": "pending",
    "visibility": "1",
    "test_code6": null,
    "total_views": null,
    "id": "85031584",
    "loginId": "1758823",
    "entityType": "1",
    "sortOrder": "1446",
    "entityIdParent": "85595609",
    "titleTextEncoded": "Last-man-on-the-moon-Gene-Cernan-dies-at-82",
    "category": "",
    "duration": 20,
    "settings": "",
    "asset": {
        "type": "youtube",
        "thumbnailUrl": "https:\/\/i.ytimg.com\/vi\/9Of8eqpZY8k\/hqdefault.jpg",
        "uploadDate": 1484607970,
        "videoId": "9Of8eqpZY8k",
        "title": "Last man on the moon Gene Cernan dies at 82",
        "description": "\"Eugene Cernan\":https:\/\/en.wikipedia.org\/wiki\/Eugene_Cernan the last man to walk on the moon as skipper of Apollo 17 in December 1972, has died at the age ...",
        "author": "euronews (in English)",
        "mediaDuration": 20,
        "prettyDuration": "00:00:20",
        "views": "503"
    },
    "transcripts": "",
    "test_code": null,
    "test_code2": null,
    "test_code3": null,
    "test_code4": null,
    "test_code5": null
}