{
    "title": "(AKMU) \uc624\ub79c \ub0a0 \uc624\ub79c \ubc24 Last Goodbye - Sungha Jung",
    "description": "Sungha http:\/\/www.sunghajung.com arranged and played \"\uc624\ub79c \ub0a0 \uc624\ub79c \ubc24\" by AKMU.",
    "referenceId": "EPlX8XjnuiI",
    "date_created": "1486189865",
    "date_modified": "1486346618",
    "tags": "",
    "sourceId": "4",
    "VIDEO_LENGTH": "SHORT",
    "status": "pending",
    "visibility": "1",
    "test_code6": null,
    "total_views": null,
    "id": "85292260",
    "loginId": "1758823",
    "entityType": "1",
    "sortOrder": "1689",
    "entityIdParent": "85595609",
    "titleTextEncoded": "AKMU-\uc624\ub79c-\ub0a0-\uc624\ub79c-\ubc24-Last-Goodbye-Sungha-Jung",
    "category": "",
    "duration": 177,
    "settings": "",
    "asset": {
        "type": "youtube",
        "thumbnailUrl": "https:\/\/i.ytimg.com\/vi\/EPlX8XjnuiI\/hqdefault.jpg",
        "uploadDate": 1486189865,
        "videoId": "EPlX8XjnuiI",
        "title": "(AKMU) \uc624\ub79c \ub0a0 \uc624\ub79c \ubc24 Last Goodbye - Sungha Jung",
        "description": "Sungha http:\/\/www.sunghajung.com arranged and played \"\uc624\ub79c \ub0a0 \uc624\ub79c \ubc24\" by AKMU.",
        "author": "jwcfree",
        "mediaDuration": 177,
        "prettyDuration": "00:02:57",
        "views": "61793"
    },
    "transcripts": "",
    "test_code": null,
    "test_code2": null,
    "test_code3": null,
    "test_code4": null,
    "test_code5": null
}