{
    "title": "TRANSFORMERS: THE LAST KNIGHT SUPER BOWL AD REVIEW",
    "description": "Ellis reviews the new Super Bowl spot for Guardians Vol 2! CHECK OUT LOOT CRATE: lootcrate.com\/schmoes *** Save 10% with Promo Code \u201cSCHMOES\u201d ...",
    "referenceId": "jCptRLe3aD0",
    "date_created": "1486339762",
    "date_modified": "1486346618",
    "tags": "",
    "sourceId": "4",
    "VIDEO_LENGTH": "SHORT",
    "status": "pending",
    "visibility": "1",
    "test_code6": null,
    "total_views": null,
    "id": "85292234",
    "loginId": "1758823",
    "entityType": "1",
    "sortOrder": "1714",
    "entityIdParent": "85595609",
    "titleTextEncoded": "TRANSFORMERS-THE-LAST-KNIGHT-SUPER-BOWL-AD-REVIEW",
    "category": "",
    "duration": 164,
    "settings": "",
    "asset": {
        "type": "youtube",
        "thumbnailUrl": "https:\/\/i.ytimg.com\/vi\/jCptRLe3aD0\/hqdefault.jpg",
        "uploadDate": 1486339762,
        "videoId": "jCptRLe3aD0",
        "title": "TRANSFORMERS: THE LAST KNIGHT SUPER BOWL AD REVIEW",
        "description": "Ellis reviews the new Super Bowl spot for Guardians Vol 2! CHECK OUT LOOT CRATE: lootcrate.com\/schmoes *** Save 10% with Promo Code \u201cSCHMOES\u201d ...",
        "author": "schmoesknow",
        "mediaDuration": 164,
        "prettyDuration": "00:02:44",
        "views": "1504"
    },
    "transcripts": "",
    "test_code": null,
    "test_code2": null,
    "test_code3": null,
    "test_code4": null,
    "test_code5": null
}