{
    "title": "I swear, this is the LAST TIME",
    "description": "YESTERDAY'S VLOG - https:\/\/youtu.be\/d8j86c-jJWI SHIRTS, STICKERS & MORE - http:\/\/Motonosity.com A perfect storm of mistakes resulted in me running out ...",
    "referenceId": "ixKYlmb1lM4",
    "date_created": "1486509354",
    "date_modified": "1486692229",
    "tags": "",
    "sourceId": "4",
    "VIDEO_LENGTH": "LONG",
    "status": "pending",
    "visibility": "1",
    "test_code6": null,
    "total_views": null,
    "id": "85337148",
    "loginId": "1758823",
    "entityType": "1",
    "sortOrder": "1729",
    "entityIdParent": "85595609",
    "titleTextEncoded": "I-swear-this-is-the-LAST-TIME",
    "category": "",
    "duration": 926,
    "settings": "",
    "asset": {
        "type": "youtube",
        "thumbnailUrl": "https:\/\/i.ytimg.com\/vi\/ixKYlmb1lM4\/hqdefault.jpg",
        "uploadDate": 1486509354,
        "videoId": "ixKYlmb1lM4",
        "title": "I swear, this is the LAST TIME",
        "description": "YESTERDAY'S VLOG - https:\/\/youtu.be\/d8j86c-jJWI SHIRTS, STICKERS & MORE - http:\/\/Motonosity.com A perfect storm of mistakes resulted in me running out ...",
        "author": "Motonosity",
        "mediaDuration": 926,
        "prettyDuration": "00:15:26",
        "views": "42603"
    },
    "transcripts": "",
    "test_code": null,
    "test_code2": null,
    "test_code3": null,
    "test_code4": null,
    "test_code5": null
}