{
    "title": "My LAST vignette.    vicdibitetto.net",
    "description": "",
    "referenceId": "BctjP5ERijw",
    "date_created": "1487690199",
    "date_modified": "1487729023",
    "tags": "",
    "sourceId": "4",
    "VIDEO_LENGTH": "SHORT",
    "status": "pending",
    "visibility": "1",
    "test_code6": null,
    "total_views": null,
    "id": "85464621",
    "loginId": "1758823",
    "entityType": "1",
    "sortOrder": "1995",
    "entityIdParent": "85595609",
    "titleTextEncoded": "My-LAST-vignette-vicdibitetto-net",
    "category": "",
    "duration": 89,
    "settings": "",
    "asset": {
        "type": "youtube",
        "thumbnailUrl": "https:\/\/i.ytimg.com\/vi\/BctjP5ERijw\/hqdefault.jpg",
        "uploadDate": 1487690199,
        "videoId": "BctjP5ERijw",
        "title": "My LAST vignette.    vicdibitetto.net",
        "description": "",
        "author": "Vic Dibitetto",
        "mediaDuration": 89,
        "prettyDuration": "00:01:29",
        "views": "2122"
    },
    "transcripts": "",
    "test_code": null,
    "test_code2": null,
    "test_code3": null,
    "test_code4": null,
    "test_code5": null
}