{
    "title": "The Last Federation - Live!",
    "description": "Since I love this game - on the day there was a sale on, so sorry that the $5 deal isn't available any more.",
    "referenceId": "JB0WSG4yj44",
    "date_created": "1488664007",
    "date_modified": "1488766259",
    "tags": "",
    "sourceId": "4",
    "VIDEO_LENGTH": "LONG",
    "status": "pending",
    "visibility": "1",
    "test_code6": null,
    "total_views": null,
    "id": "85697674",
    "loginId": "1758823",
    "entityType": "1",
    "sortOrder": "2171",
    "entityIdParent": "85595609",
    "titleTextEncoded": "The-Last-Federation-Live",
    "category": "",
    "duration": 6221,
    "settings": "",
    "asset": {
        "type": "youtube",
        "thumbnailUrl": "https:\/\/i.ytimg.com\/vi\/JB0WSG4yj44\/hqdefault.jpg",
        "uploadDate": 1488664007,
        "videoId": "JB0WSG4yj44",
        "title": "The Last Federation - Live!",
        "description": "Since I love this game - on the day there was a sale on, so sorry that the $5 deal isn't available any more.",
        "author": "Scott Manley",
        "mediaDuration": 6221,
        "prettyDuration": "01:43:41",
        "views": "19461"
    },
    "transcripts": "",
    "test_code": null,
    "test_code2": null,
    "test_code3": null,
    "test_code4": null,
    "test_code5": null
}