{
    "title": "NCT DREAM - My First and Last @Show Music Core Stage Mix",
    "description": "NCT DREAM - My First and Last \uad50\ucc28\ud3b8\uc9d1(Stage Mix) @Show music core \uc5d4\uc2dc\ud2f0 \ub4dc\ub9bc - \ub9c8\uc9c0\ub9c9 \uccab\uc0ac\ub791 \uc1fc\uc74c\uc545\uc911\uc2ec \ubb34\ub300 \ubaa8\uc544\ubcf4\uae30! Show Music Core 20170211 ...",
    "referenceId": "p21bquldO58",
    "date_created": "1488514736",
    "date_modified": "1488766259",
    "tags": "",
    "sourceId": "4",
    "VIDEO_LENGTH": "SHORT",
    "status": "pending",
    "visibility": "1",
    "test_code6": null,
    "total_views": null,
    "id": "85697702",
    "loginId": "1758823",
    "entityType": "1",
    "sortOrder": "2143",
    "entityIdParent": "85595609",
    "titleTextEncoded": "NCT-DREAM-My-First-and-Last-Show-Music-Core-Stage-Mix",
    "category": "",
    "duration": 200,
    "settings": "",
    "asset": {
        "type": "youtube",
        "thumbnailUrl": "https:\/\/i.ytimg.com\/vi\/p21bquldO58\/hqdefault.jpg",
        "uploadDate": 1488514736,
        "videoId": "p21bquldO58",
        "title": "NCT DREAM - My First and Last @Show Music Core Stage Mix",
        "description": "NCT DREAM - My First and Last \uad50\ucc28\ud3b8\uc9d1(Stage Mix) @Show music core \uc5d4\uc2dc\ud2f0 \ub4dc\ub9bc - \ub9c8\uc9c0\ub9c9 \uccab\uc0ac\ub791 \uc1fc\uc74c\uc545\uc911\uc2ec \ubb34\ub300 \ubaa8\uc544\ubcf4\uae30! Show Music Core 20170211 ...",
        "author": "MBCkpop",
        "mediaDuration": 200,
        "prettyDuration": "00:03:20",
        "views": "44453"
    },
    "transcripts": "",
    "test_code": null,
    "test_code2": null,
    "test_code3": null,
    "test_code4": null,
    "test_code5": null
}