{
    "title": "\u0baa\u0bb3\u0bcd\u0bb3\u0bbf \u0bb5\u0bbe\u0bb4\u0bcd\u0b95\u0bcd\u0b95\u0bc8\u0baf\u0bbf\u0bb2\u0bcd \u0b87\u0bb0\u0ba3\u0bcd\u0b9f\u0bc1 - Last Bench Vs First Bench | Tamil Memes",
    "description": "Credits : Buddies Entertainment.",
    "referenceId": "-5kEhiLj0lk",
    "date_created": "1488829679",
    "date_modified": "1489111954",
    "tags": "",
    "sourceId": "4",
    "VIDEO_LENGTH": "LONG",
    "status": "pending",
    "visibility": "1",
    "test_code6": null,
    "total_views": null,
    "id": "85743154",
    "loginId": "1758823",
    "entityType": "1",
    "sortOrder": "2182",
    "entityIdParent": "85595609",
    "titleTextEncoded": "\u0baa\u0bb3-\u0bb3-\u0bb5-\u0bb4-\u0b95-\u0b95-\u0baf-\u0bb2-\u0b87\u0bb0\u0ba3-\u0b9f-Last-Bench-Vs-First-Bench-Tamil-Memes",
    "category": "",
    "duration": 449,
    "settings": "",
    "asset": {
        "type": "youtube",
        "thumbnailUrl": "https:\/\/i.ytimg.com\/vi\/-5kEhiLj0lk\/hqdefault.jpg",
        "uploadDate": 1488829679,
        "videoId": "-5kEhiLj0lk",
        "title": "\u0baa\u0bb3\u0bcd\u0bb3\u0bbf \u0bb5\u0bbe\u0bb4\u0bcd\u0b95\u0bcd\u0b95\u0bc8\u0baf\u0bbf\u0bb2\u0bcd \u0b87\u0bb0\u0ba3\u0bcd\u0b9f\u0bc1 - Last Bench Vs First Bench | Tamil Memes",
        "description": "Credits : Buddies Entertainment.",
        "author": "Watch Me",
        "mediaDuration": 449,
        "prettyDuration": "00:07:29",
        "views": "7281"
    },
    "transcripts": "",
    "test_code": null,
    "test_code2": null,
    "test_code3": null,
    "test_code4": null,
    "test_code5": null
}